LICENSE
MANIFEST.in
README.md
jinja_app_loader.py
setup.py
jinja_app_loader.egg-info/PKG-INFO
jinja_app_loader.egg-info/SOURCES.txt
jinja_app_loader.egg-info/dependency_links.txt
jinja_app_loader.egg-info/top_level.txt