Metadata-Version: 1.1
Name: jinja-app-loader
Version: 1.0.2
Summary: Jinja 2 loader for resource-based apps.
Home-page: https://github.com/imbolc/jinja_app_loader
Author: Imbolc
Author-email: imbolc@imbolc.name
License: ISC
Platform: UNKNOWN
Classifier: Development Status :: 4 - Beta
Classifier: Intended Audience :: Developers
Classifier: License :: OSI Approved :: ISC License (ISCL)
Classifier: Programming Language :: Python
Classifier: Programming Language :: Python :: 3
